checkbox_sdk/__init__.py
checkbox_sdk/client/__init__.py
checkbox_sdk/client/api/__init__.py
checkbox_sdk/client/api/base.py
checkbox_sdk/client/api/branches.py
checkbox_sdk/client/api/cash_registers.py
checkbox_sdk/client/api/cashier.py
checkbox_sdk/client/api/currency.py
checkbox_sdk/client/api/extended_reports.py
checkbox_sdk/client/api/goods.py
checkbox_sdk/client/api/invoices.py
checkbox_sdk/client/api/nova_post.py
checkbox_sdk/client/api/orders.py
checkbox_sdk/client/api/organization.py
checkbox_sdk/client/api/prepayment_receipts.py
checkbox_sdk/client/api/receipts.py
checkbox_sdk/client/api/reports.py
checkbox_sdk/client/api/shifts.py
checkbox_sdk/client/api/tax.py
checkbox_sdk/client/api/transactions.py
checkbox_sdk/client/api/webhook.py
checkbox_sdk/client/asynchronous.py
checkbox_sdk/client/base.py
checkbox_sdk/client/rate_limit.py
checkbox_sdk/client/synchronous.py
checkbox_sdk/client/utils.py
checkbox_sdk/consts.py
checkbox_sdk/exceptions.py
checkbox_sdk/methods/__init__.py
checkbox_sdk/methods/base.py
checkbox_sdk/methods/branches.py
checkbox_sdk/methods/cash_register.py
checkbox_sdk/methods/cashier.py
checkbox_sdk/methods/currency.py
checkbox_sdk/methods/extended_reports.py
checkbox_sdk/methods/goods.py
checkbox_sdk/methods/invoices.py
checkbox_sdk/methods/nova_post.py
checkbox_sdk/methods/orders.py
checkbox_sdk/methods/organization.py
checkbox_sdk/methods/prepayment_receipts.py
checkbox_sdk/methods/receipts.py
checkbox_sdk/methods/reports.py
checkbox_sdk/methods/shifts.py
checkbox_sdk/methods/tax.py
checkbox_sdk/methods/transactions.py
checkbox_sdk/methods/webhook.py
checkbox_sdk/storage/__init__.py
checkbox_sdk/storage/simple.py
checkbox_sdk-1.4.0.dist-info/LICENSE
checkbox_sdk-1.4.0.dist-info/METADATA
checkbox_sdk-1.4.0.dist-info/WHEEL
checkbox_sdk-1.4.0.dist-info/RECORD
