Metadata-Version: 2.3
Name: checkbox-sdk
Version: 1.4.0
Summary: Ukraine checkbox api python sdk
License: MIT
Keywords: python,sdk
Author: Roman Telezhynskyi
Author-email: dismine@gmail.com
Maintainer: Roman Telezhynskyi
Maintainer-email: dismine@gmail.com
Requires-Python: >=3.9,<4.0
Classifier: Development Status :: 5 - Production/Stable
Classifier: Intended Audience :: Developers
Classifier: Programming Language :: Python
Classifier: Programming Language :: Python :: 3
Classifier: Programming Language :: Python :: 3 :: Only
Classifier: License :: OSI Approved :: MIT License
Requires-Dist: httpcore (>=1.0.7,<2.0.0)
Requires-Dist: httpx (>=0.28.1,<0.29.0)
Requires-Dist: pyjwt (>=2.4.0,<3.0.0)
Project-URL: Changelog, https://github.com/dismine/checkbox-sdk/blob/main/CHANGELOG.md
Project-URL: Documentation, https://checkbox-sdk.readthedocs.io
Project-URL: Repository, https://github.com/dismine/checkbox-sdk.git
